{"type":"Feature","geometry":{"type":"Point","coordinates":[35.512547,32.950401]},"properties":{"type":"Village","group":"Palestinian","status":"Depopulated","id":886,"name_en":"Al Dhahiriyya Al Fauq'a","name_ar":null,"name_he":null,"slug":"al-dhahiriyya-al-fauqa","district_1945":"Safad","district_isr":null,"type_special":null,"pop_1922":null,"pop_1931":null,"type_1945":"Village","grp_1945":"Palestinian","pop_1945":null,"pal_1945":null,"jsh_1945":null,"change_2016":"Depopulated","type_2016":null,"grp_2016":null,"pop_2016":null,"pal_2016":null,"jsh_2016":null,"oth_2016":null,"start":null,"end":null,"lat":32.950401,"lng":35.512547,"map_20k":"yes","id_zo":null,"id_pr":989,"id_as":null,"id_old":3322,"url_pr":"GeoPoints/al_Zahiriyya_al_Fauq_a_989"}}