{"type":"Feature","geometry":{"type":"Point","coordinates":[35.273027,32.002837]},"properties":{"type":"Village","group":"Palestinian","status":"Remaining","id":790,"name_en":"Al Mazra'a Al Sharqiyya","name_ar":"المَزْرَعَة الشَرْقِيَّة","name_he":null,"slug":"al-mazraa-al-sharqiyya","district_1945":"Ramallah","district_isr":"West Bank","type_special":null,"pop_1922":824,"pop_1931":1191,"type_1945":"Village","grp_1945":"Palestinian","pop_1945":1400,"pal_1945":1400,"jsh_1945":null,"change_2016":"Remaining","type_2016":"Village","grp_2016":"Palestinian","pop_2016":5752,"pal_2016":5752,"jsh_2016":null,"oth_2016":null,"start":null,"end":null,"lat":32.002837,"lng":35.273027,"map_20k":"yes","id_zo":null,"id_pr":1051,"id_as":null,"id_old":3226,"url_pr":"GeoPoints/al_Mazra_a_al_Sharqiya_1051"}}