{"type":"Feature","geometry":{"type":"Point","coordinates":[35.098138,32.992345]},"properties":{"type":"Settlement","group":"Jewish","status":"Remaining","id":10883,"name_en":"Evron (Ga'aton)","name_ar":null,"name_he":"עברון","slug":"evron-gaaton","district_1945":"Acre","district_isr":"Northern","type_special":null,"pop_1922":null,"pop_1931":null,"type_1945":"Settlement","grp_1945":"Jewish","pop_1945":null,"pal_1945":null,"jsh_1945":null,"change_2016":"Remaining","type_2016":"Settlement","grp_2016":"Jewish","pop_2016":800,"pal_2016":null,"jsh_2016":700,"oth_2016":100,"start":1945,"end":null,"lat":32.992345,"lng":35.098138,"map_20k":"yes","id_zo":null,"id_pr":null,"id_as":null,"id_old":4337,"url_pr":null}}