{"type":"Feature","geometry":{"type":"Point","coordinates":[35.139372,32.934105]},"properties":{"type":"Amalgamated","group":"Palestinian","status":"Remaining","id":57,"name_en":"Makr","name_ar":null,"name_he":null,"slug":"makr","district_1945":"Acre","district_isr":"Northern","type_special":null,"pop_1922":281,"pop_1931":331,"type_1945":"Village","grp_1945":"Palestinian","pop_1945":490,"pal_1945":490,"jsh_1945":null,"change_2016":"Remaining","type_2016":"Amalgamated","grp_2016":"Palestinian","pop_2016":null,"pal_2016":null,"jsh_2016":null,"oth_2016":null,"start":null,"end":null,"lat":32.934105,"lng":35.139372,"map_20k":"yes","id_zo":null,"id_pr":1394,"id_as":null,"id_old":2493,"url_pr":"GeoPoints/Makr_1394"}}