{"type":"Feature","geometry":{"type":"Point","coordinates":[34.82421,31.92322]},"properties":{"type":"Settlement","group":"Jewish","status":"Newly built","id":10854,"name_en":"Nezer Sereni","name_ar":"Nezer Sereni","name_he":"נצר סרני","slug":"nezer-sereni","district_1945":null,"district_isr":"Central","type_special":null,"pop_1922":null,"pop_1931":null,"type_1945":null,"grp_1945":null,"pop_1945":null,"pal_1945":null,"jsh_1945":null,"change_2016":"Newly built","type_2016":"Settlement","grp_2016":"Jewish","pop_2016":800,"pal_2016":null,"jsh_2016":700,"oth_2016":100,"start":1948,"end":null,"lat":31.92322,"lng":34.82421,"map_20k":"no","id_zo":null,"id_pr":null,"id_as":null,"id_old":4314,"url_pr":null}}