{"type":"Feature","geometry":{"type":"Point","coordinates":[35.51378,32.4404]},"properties":{"type":"Settlement","group":"Jewish","status":"Remaining","id":11113,"name_en":"Sede Eliyyahu","name_ar":"Sede Eliyyahu","name_he":"שדה אליהו","slug":"sede-eliyyahu","district_1945":"Galilee","subdistrict_1945":"Beisan","district_isr":"Northern","type_special":null,"pop_1922":null,"pop_1931":null,"type_1945":"Settlement","grp_1945":"Jewish","pop_1945":null,"pal_1945":null,"jsh_1945":null,"change_2016":"Remaining","type_2016":"Settlement","grp_2016":"Jewish","pop_2016":700,"pal_2016":null,"jsh_2016":700,"oth_2016":null,"start":1939,"end":null,"lat":32.4404,"lng":35.51378,"map_20k":true,"id_zo":null,"id_pr":null,"id_as":null,"id_old":4514,"id_pq":733,"url_pr":null,"url_pq_en":null,"url_pq_ar":null,"notes":null}}