{"type":"Feature","geometry":{"type":"Point","coordinates":[35.594105,33.007992]},"properties":{"type":"Community","group":"Palestinian","status":"Depopulated","id":884,"name_en":"Yarda","name_ar":"يردا","name_he":"יַרְדָא","slug":"yarda","district_1945":"Safad","district_isr":null,"type_special":null,"pop_1922":null,"pop_1931":13,"type_1945":"Community","grp_1945":"Palestinian","pop_1945":null,"pal_1945":null,"jsh_1945":null,"change_2016":"Depopulated","type_2016":null,"grp_2016":null,"pop_2016":null,"pal_2016":null,"jsh_2016":null,"oth_2016":null,"start":null,"end":"1948-07-18T00:00:00.000Z","lat":33.007992,"lng":35.594105,"map_20k":"yes","id_zo":49206,"id_pr":1348,"id_as":412,"id_old":3320,"url_pr":"Safad/Yarda"}}