{"type":"Feature","geometry":{"type":"Point","coordinates":[35.010848,32.266277]},"properties":{"type":"City","group":"Palestinian","status":"Remaining","id":1024,"name_en":"al-Tayyiba","name_ar":"الطيبة","name_he":null,"slug":"al-tayyiba-tulkarm","district_1945":"Samaria","subdistrict_1945":"Tulkarem","district_isr":"Central","type_special":null,"pop_1922":2350,"pop_1931":2944,"type_1945":"Village","grp_1945":"Palestinian","pop_1945":4400,"pal_1945":4290,"jsh_1945":110,"change_2016":"Remaining","type_2016":"City","grp_2016":"Palestinian","pop_2016":41500,"pal_2016":41500,"jsh_2016":null,"oth_2016":null,"start":null,"end":null,"lat":32.266277,"lng":35.010848,"map_20k":"yes","id_zo":null,"id_pr":1627,"id_as":null,"id_old":3460,"id_pq":451,"url_pr":"GeoPoints/Tayyiba_1627","url_pq_en":null,"url_pq_ar":null}}